[
  {
    "level": 1,
    "xp": 0
  },
  {
    "level": 2,
    "xp": 1250
  },
  {
    "level": 3,
    "xp": 3750
  },
  {
    "level": 4,
    "xp": 7250
  },
  {
    "level": 5,
    "xp": 11750
  },
  {
    "level": 6,
    "xp": 17750
  },
  {
    "level": 7,
    "xp": 25250
  },
  {
    "level": 8,
    "xp": 34250
  },
  {
    "level": 9,
    "xp": 45250
  },
  {
    "level": 10,
    "xp": 58250
  },
  {
    "level": 11,
    "xp": 71399
  },
  {
    "level": 12,
    "xp": 98983
  },
  {
    "level": 13,
    "xp": 115359
  },
  {
    "level": 14,
    "xp": 133634
  },
  {
    "level": 15,
    "xp": 154028
  },
  {
    "level": 16,
    "xp": 176787
  },
  {
    "level": 17,
    "xp": 202186
  },
  {
    "level": 18,
    "xp": 230531
  },
  {
    "level": 19,
    "xp": 262164
  },
  {
    "level": 20,
    "xp": 297466
  },
  {
    "level": 21,
    "xp": 336863
  },
  {
    "level": 22,
    "xp": 380830
  },
  {
    "level": 23,
    "xp": 429897
  },
  {
    "level": 24,
    "xp": 484655
  },
  {
    "level": 25,
    "xp": 545764
  },
  {
    "level": 26,
    "xp": 613961
  },
  {
    "level": 27,
    "xp": 690068
  },
  {
    "level": 28,
    "xp": 775003
  },
  {
    "level": 29,
    "xp": 869790
  },
  {
    "level": 30,
    "xp": 975572
  },
  {
    "level": 31,
    "xp": 1093624
  },
  {
    "level": 32,
    "xp": 1225370
  },
  {
    "level": 33,
    "xp": 1372398
  },
  {
    "level": 34,
    "xp": 1536481
  },
  {
    "level": 35,
    "xp": 1700564
  },
  {
    "level": 36,
    "xp": 1883680
  },
  {
    "level": 37,
    "xp": 2088037
  },
  {
    "level": 38,
    "xp": 2316099
  },
  {
    "level": 39,
    "xp": 2570616
  },
  {
    "level": 40,
    "xp": 2854656
  },
  {
    "level": 41,
    "xp": 3171644
  },
  {
    "level": 42,
    "xp": 3525402
  },
  {
    "level": 43,
    "xp": 3920195
  },
  {
    "level": 44,
    "xp": 4360783
  },
  {
    "level": 45,
    "xp": 4852479
  },
  {
    "level": 46,
    "xp": 5401211
  },
  {
    "level": 47,
    "xp": 6013595
  },
  {
    "level": 48,
    "xp": 6697015
  },
  {
    "level": 49,
    "xp": 7459711
  },
  {
    "level": 50,
    "xp": 8310879
  },
  {
    "level": 51,
    "xp": 9260782
  },
  {
    "level": 52,
    "xp": 10320873
  },
  {
    "level": 53,
    "xp": 11503934
  },
  {
    "level": 54,
    "xp": 12824230
  },
  {
    "level": 55,
    "xp": 14297680
  },
  {
    "level": 56,
    "xp": 15942050
  },
  {
    "level": 57,
    "xp": 17777166
  },
  {
    "level": 58,
    "xp": 19825155
  },
  {
    "level": 59,
    "xp": 22110710
  },
  {
    "level": 60,
    "xp": 24661389
  },
  {
    "level": 61,
    "xp": 27507946
  },
  {
    "level": 62,
    "xp": 30684703
  },
  {
    "level": 63,
    "xp": 34229963
  },
  {
    "level": 64,
    "xp": 38186473
  },
  {
    "level": 65,
    "xp": 42601938
  },
  {
    "level": 66,
    "xp": 47529596
  },
  {
    "level": 67,
    "xp": 53666776
  },
  {
    "level": 68,
    "xp": 60515868
  },
  {
    "level": 69,
    "xp": 68159454
  },
  {
    "level": 70,
    "xp": 76689695
  },
  {
    "level": 71,
    "xp": 86209443
  },
  {
    "level": 72,
    "xp": 96833481
  },
  {
    "level": 73,
    "xp": 108689907
  },
  {
    "level": 74,
    "xp": 121921678
  },
  {
    "level": 75,
    "xp": 136688334
  },
  {
    "level": 76,
    "xp": 153167922
  },
  {
    "level": 77,
    "xp": 171559142
  },
  {
    "level": 78,
    "xp": 192083743
  },
  {
    "level": 79,
    "xp": 214989197
  },
  {
    "level": 80,
    "xp": 240551683
  },
  {
    "level": 81,
    "xp": 269079417
  },
  {
    "level": 82,
    "xp": 300916368
  },
  {
    "level": 83,
    "xp": 336446405
  },
  {
    "level": 84,
    "xp": 376097926
  },
  {
    "level": 85,
    "xp": 420349023
  },
  {
    "level": 86,
    "xp": 469733247
  },
  {
    "level": 87,
    "xp": 524846040
  },
  {
    "level": 88,
    "xp": 586351916
  },
  {
    "level": 89,
    "xp": 654992473
  },
  {
    "level": 90,
    "xp": 731595334
  },
  {
    "level": 91,
    "xp": 817084126
  },
  {
    "level": 92,
    "xp": 914489617
  },
  {
    "level": 93,
    "xp": 1018962144
  },
  {
    "level": 94,
    "xp": 1137785484
  },
  {
    "level": 95,
    "xp": 1270392331
  },
  {
    "level": 96,
    "xp": 1418381572
  },
  {
    "level": 97,
    "xp": 1583537564
  },
  {
    "level": 98,
    "xp": 1767851651
  },
  {
    "level": 99,
    "xp": 2000000000
  }
]